lino_amici/__init__.py
lino_amici/lib/__init__.py
lino_amici/lib/amici/__init__.py
lino_amici/lib/amici/custom_layouts.py
lino_amici/lib/amici/help_texts.py
lino_amici/lib/amici/models.py
lino_amici/lib/amici/settings.py
lino_amici/lib/amici/user_types.py
lino_amici/lib/amici/workflows.py
lino_amici/lib/amici/locale/django.pot
lino_amici/lib/amici/locale/de/LC_MESSAGES/django.mo
lino_amici/lib/amici/locale/de/LC_MESSAGES/django.po
lino_amici/lib/amici/locale/et/LC_MESSAGES/django.mo
lino_amici/lib/amici/locale/et/LC_MESSAGES/django.po
lino_amici/lib/amici/locale/fr/LC_MESSAGES/django.mo
lino_amici/lib/amici/locale/fr/LC_MESSAGES/django.po
lino_amici/lib/cal/__init__.py
lino_amici/lib/cal/models.py
lino_amici/lib/cal/fixtures/demo.py
lino_amici/lib/cal/fixtures/demo2.py
lino_amici/lib/cal/fixtures/std.py
lino_amici/lib/contacts/__init__.py
lino_amici/lib/contacts/models.py
lino_amici/lib/contacts/fixtures/__init__.py
lino_amici/lib/contacts/fixtures/demo.py
lino_amici/lib/contacts/fixtures/std.py
lino_amici/lib/households/__init__.py
lino_amici/lib/households/models.py
lino_amici/lib/households/fixtures/__init__.py
lino_amici/lib/households/fixtures/demo.py
lino_amici/lib/households/fixtures/std.py
lino_amici/lib/users/__init__.py
lino_amici/lib/users/models.py
lino_amici/lib/users/ui.py
lino_amici/lib/users/fixtures/__init__.py
lino_amici/lib/users/fixtures/demo.py
lino_amici/lib/users/fixtures/demo2.py
lino_amici/lib/users/fixtures/demo_users.py
lino_amici/projects/__init__.py
lino_amici/projects/amici1/__init__.py
lino_amici/projects/amici1/google_creds.json
lino_amici/projects/amici1/initdb_tmp
lino_amici/projects/amici1/manage.py
lino_amici/projects/amici1/settings.py
lino_amici/projects/amici1/show_birthdays.py
lino_amici/projects/amici1/fixtures/__init__.py
lino_amici/projects/amici1/fixtures/demo.py
lino_amici/projects/amici1/tests/__init__.py
lino_amici/projects/amici1/tests/test_insert_person.py
lino_amici-26.1.0.dist-info/METADATA
lino_amici-26.1.0.dist-info/WHEEL
lino_amici-26.1.0.dist-info/licenses/COPYING
lino_amici-26.1.0.dist-info/RECORD
